{
"DICT_F_FLAG":"",
"DICT_NAME_LAYER":"0",
"S_PUBLIC":"1",
"TABLE_SELECT":"",
"S_MTIME":"2020-02-14 11:22:23:222",
"TABLE_WHERE":"",
"DICT_DIS_FORMAT":"",
"PRO_FLAG":"1",
"DICT_TYPE":"2",
"DICT_SRC_ID":"",
"DICT_CLASS":"",
"TABLE_ID":"SYS_MENU_INFO",
"DICT_F_NAME":"menu_name",
"DICT_NAME":"菜单树",
"DICT_DATA_SOURCE":"",
"DICT_IS_INNER":"2",
"DICT_F_LEAF":"",
"DICT_ID":"SYS_MENU_INFO",
"S_FLAG":"1",
"DICT_LOAD_TYPE":"2",
"DICT_EXPRESSION":"",
"_ROWNUM_":"0",
"DICT_ROOT":"",
"DICT_F_PATH":"",
"DICT_DIS_LAYER":"0",
"DICT_F_PARENT":"parent_code",
"DICT_F_LEVEL":"level",
"TABLE_ORDER":"",
"_PK_":"SYS_MENU_INFO",
"DICT_CHILD_ID":"",
"DICT_F_CMPY":"",
"S_CMPY":"CSDC",
"DICT_F_ID":"menu_code"
}